{
    "jordon_1993-04-21": {
        "username": "jordon",
        "oracle_name": "Oracle of the First Flame",
        "planetary_ruler": "Venus",
        "date_of_birth": "1993-04-21",
        "time_of_birth": "03:41",
        "location": "Halifax, NS",
        "rulership_system": "traditional",
        "chart": {
            "sun": {
                "sign": "Taurus",
                "degree": 0.5,
                "house": 1,
                "motion": "Direct",
                "decan": {
                    "order": "First",
                    "ruler": "Venus"
                }
            },
            "moon": {
                "sign": "Leo",
                "degree": 13.4,
                "house": 4,
                "motion": "Direct",
                "decan": {
                    "order": "Second",
                    "ruler": "Jupiter"
                }
            },
            "mercury": {
                "sign": "Aries",
                "degree": 22.1,
                "house": 12,
                "motion": "Retrograde",
                "decan": {
                    "order": "Third",
                    "ruler": "Mars"
                }
            },
            "venus": {
                "sign": "Pisces",
                "degree": 27.9,
                "house": 11,
                "motion": "Direct",
                "decan": {
                    "order": "Third",
                    "ruler": "Mars"
                }
            },
            "mars": {
                "sign": "Gemini",
                "degree": 5.2,
                "house": 2,
                "motion": "Direct",
                "decan": {
                    "order": "First",
                    "ruler": "Mercury"
                }
            },
            "ascendant": {
                "sign": "Aries",
                "degree": 15.0,
                "house": 1,
                "motion": "Direct",
                "decan": {
                    "order": "Second",
                    "ruler": "Sun"
                }
            }
        },
        "status": "created",
        "prophecy_arc": {
            "status": "uninitiated",
            "seasonal_seed": null
        }
    }
}